call_useragent/__init__.py
call_useragent/head.py
call_useragent-0.0.1.dist-info/LICENSE
call_useragent-0.0.1.dist-info/METADATA
call_useragent-0.0.1.dist-info/WHEEL
call_useragent-0.0.1.dist-info/top_level.txt
call_useragent-0.0.1.dist-info/RECORD
