Metadata-Version: 2.1
Name: call_useragent
Version: 0.0.1
Summary: 由于国内网络限制无法使用 fake_useragent 库而制作的替代品
Home-page: https://github.com/dream-pioneer/call_useragent
Author: dream-pioneer
Author-email: dream.pioneer537@gmail.com
License: UNKNOWN
Platform: UNKNOWN
License-File: LICENSE
